mdlsum/__init__.py
mdlsum/cli.py
mdlsum/download.py
mdlsum/summarize.py
mdlsum/transcribe.py
mdlsum_cli-0.2.1.dist-info/METADATA
mdlsum_cli-0.2.1.dist-info/WHEEL
mdlsum_cli-0.2.1.dist-info/entry_points.txt
mdlsum_cli-0.2.1.dist-info/top_level.txt
mdlsum_cli-0.2.1.dist-info/RECORD
