Metadata-Version: 2.1
Name: mdlsum-cli
Version: 0.2.1
Summary: A CLI tool to download, transcribe, and summarize YouTube videos.
Home-page: https://github.com/yourusername/mdlsum-cli
Author: SidRT
Author-email: avsdhz3x2@mozmail.com
License: UNKNOWN
Platform: UNKNOWN
Classifier: Programming Language :: Python :: 3
Classifier: License :: OSI Approved :: MIT License
Classifier: Operating System :: OS Independent
Requires-Python: >=3.7
Requires-Dist: typer
Requires-Dist: yt-dlp
Requires-Dist: ffmpeg-python
Requires-Dist: openai
Requires-Dist: tiktoken
Requires-Dist: python-dotenv
